{
    "base": "Classic",
    "colors": {
        "imgui": {
            "border": "#7F7F7F7F",
            "border-shadow": "#00000000",
            "button": "#59669B9E",
            "button-active": "#7589CCFF",
            "button-hovered": "#667AB5C9",
            "check-mark": "#E5E5E57F",
            "child-background": "#00000000",
            "docking-empty-background": "#000000D8",
            "docking-preview": "#6666E550",
            "drag-drop-target": "#FFFF00E5",
            "frame-background": "#6D6D6D63",
            "frame-background-active": "#6B68A3AF",
            "frame-background-hovered": "#7777AF66",
            "header": "#6666E572",
            "header-active": "#8787DDCC",
            "header-hovered": "#7272E5CC",
            "menu-bar-background": "#535371FF",
            "modal-window-dim-background": "#33333359",
            "nav-highlight": "#7272E5CC",
            "nav-windowing-background": "#CCCCCC33",
            "nav-windowing-highlight": "#FFFFFFB2",
            "plot-histogram": "#E5B200FF",
            "plot-histogram-hovered": "#FF9900FF",
            "plot-lines": "#FFFFFFFF",
            "plot-lines-hovered": "#E5B200FF",
            "popup-background": "#1C1C23FF",
            "resize-grip": "#FFFFFF19",
            "resize-grip-active": "#C6D1FFE5",
            "resize-grip-hovered": "#C6D1FF99",
            "scrollbar-background": "#333F4C99",
            "scrollbar-grab": "#6666CC4C",
            "scrollbar-grab-active": "#6863CC99",
            "scrollbar-grab-hovered": "#6666CC66",
            "separator": "#7F7F7F99",
            "separator-active": "#B2B2E5FF",
            "separator-hovered": "#9999B2FF",
            "slider-grab": "#FFFFFF4C",
            "slider-grab-active": "#6863CC99",
            "tab": "#5555AEC8",
            "tab-active": "#6767B9D6",
            "tab-hovered": "#7272E5CC",
            "tab-unfocused": "#484891D1",
            "tab-unfocused-active": "#5959A6D5",
            "table-border-light": "#424247FF",
            "table-border-strong": "#4F4F72FF",
            "table-header-background": "#444460FF",
            "table-row-background": "#00000000",
            "table-row-background-alt": "#FFFFFF11",
            "text": "#E5E5E5FF",
            "text-disabled": "#999999FF",
            "text-selected-background": "#0000FF59",
            "title-background": "#535371FF",
            "title-background-active": "#535371FF",
            "title-background-collapse": "#535371FF",
            "window-background": "#000000FF",
            "window-shadow": "#000000FF"
        },
        "imhex": {
            "blur-background": "#00000000",
            "desc-button": "#282850FF",
            "desc-button-active": "#505078FF",
            "desc-button-hovered": "#3C3C64FF",
            "highlight": "#4DC69BFF",
            "IEEE-tool-sign": "#5D5D7FFF",
            "IEEE-tool-exp": "#5D7F5DFF",
            "IEEE-tool-mantissa": "#7F5D5DFF",
            "toolbar-blue": "#55A5F6FF",
            "toolbar-brown": "#DBB377FF",
            "toolbar-gray": "#E6E6E6FF",
            "toolbar-green": "#388B42FF",
            "toolbar-purple": "#672A78FF",
            "toolbar-red": "#E74C3CFF",
            "toolbar-yellow": "#F1C40FFF",
            "logger-debug":  "#388B42FF",
            "logger-info":  "#06539BFF",
            "logger-warning":  "#F1C40FFF",
            "logger-error":  "#E74C3CFF",
            "logger-fatal":  "#672A78FF",
            "achievement-unlocked":  "#F1C40FFF",
            "find-highlight":  "#672A78FF",
            "diff-added":  "#388B42FF",
            "diff-removed":  "#E74C3CFF",
            "diff-changed":  "#F1C40FFF",
            "advanced-encoding-ascii":  "#06539BFF",
            "advanced-encoding-single":  "#E74C3CFF",
            "advanced-encoding-multi":  "#F1C40FFF",
            "advanced-encoding-unknown":  "#E74C3CFF",
            "patches":  "#E74C3CFF",
            "pattern-selected":  "#06539BFF"
        },
        "imnodes": {
            "box-selector": "#5252A164",
            "box-selector-outline": "#5252A1FF",
            "grid-background": "#282832C8",
            "grid-line": "#C8C8C828",
            "grid-line-primary": "#F0F0F03C",
            "link": "#FFFFFF64",
            "link-hovered": "#6963CC99",
            "link-selected": "#6963CC99",
            "mini-map-background": "#19191964",
            "mini-map-background-hovered": "#191919C8",
            "mini-map-canvas": "#C8C8C819",
            "mini-map-canvas-outline": "#C8C8C8C8",
            "mini-map-link": "#FFFFFF64",
            "mini-map-link-selected": "#6963CC99",
            "mini-map-node-background": "#C8C8C864",
            "mini-map-node-background-hovered": "#C8C8C8FF",
            "mini-map-node-background-selected": "#C8C8F0FF",
            "mini-map-node-outline": "#C8C8C864",
            "mini-map-outline": "#96969664",
            "mini-map-outline-hovered": "#969696C8",
            "node-background": "#323232FF",
            "node-background-hovered": "#4B4B4BFF",
            "node-background-selected": "#4B4B4BFF",
            "node-outline": "#646464FF",
            "pin": "#F5CB25FF",
            "pin-hovered": "#FA8335FF",
            "title-bar": "#45458AFF",
            "title-bar-hovered": "#5252A1FF",
            "title-bar-selected": "#5252A1FF"
        },
        "implot": {
            "axis-bg": "auto",
            "axis-bg-active": "auto",
            "axis-bg-hovered": "auto",
            "axis-grid": "#E5E5E53F",
            "axis-text": "#E5E5E5FF",
            "axis-tick": "auto",
            "crosshairs": "#7F7F7FBF",
            "error-bar": "auto",
            "fill": "auto",
            "frame-bg": "#6D6D6D63",
            "inlay-text": "#E5E5E5FF",
            "legend-bg": "#1C1C23EA",
            "legend-border": "#7F7F7F7F",
            "legend-text": "#E5E5E5FF",
            "line": "auto",
            "marker-fill": "auto",
            "marker-outline": "auto",
            "plot-bg": "#00000059",
            "plot-border": "#7F7F7F7F",
            "selection": "#F7F763FF",
            "title-text": "#E5E5E5FF"
        },
        "text-editor": {
            "background": "#000080FF",
            "breakpoint": "#FF200080",
            "char-literal": "#008080FF",
            "comment": "#808080FF",
            "current-line-edge": "#00000040",
            "current-line-fill": "#00000040",
            "current-line-fill-inactive": "#80808040",
            "cursor": "#FF8000FF",
            "default": "#FFFF00FF",
            "error-marker": "#FF0000A0",
            "identifier": "#FFFF00FF",
            "keyword": "#00FFFFFF",
            "known-identifier": "#FFFFFFFF",
            "line-number": "#008080FF",
            "multi-line-comment": "#404040FF",
            "number": "#00FF00FF",
            "preproc-identifier": "#FF00FFFF",
            "preprocessor": "#008000FF",
            "punctuation": "#FFFFFFFF",
            "selection": "#00FFFF80",
            "string": "#008080FF"
        }
    },
    "image_theme": "dark",
    "name": "Classic",
    "styles": {
        "imgui": {
            "alpha": 1.0,
            "button-text-align": [
                0.5,
                0.5
            ],
            "cell-padding": [
                4.0,
                2.0
            ],
            "child-border-size": 1.0,
            "child-rounding": 0.0,
            "disabled-alpha": 0.6,
            "frame-border-size": 0.0,
            "frame-padding": [
                4.0,
                3.0
            ],
            "frame-rounding": 0.0,
            "grab-min-size": 12.0,
            "grab-rounding": 0.0,
            "indent-spacing": 10.0,
            "item-inner-spacing": [
                4.0,
                4.0
            ],
            "item-spacing": [
                8.0,
                4.0
            ],
            "popup-border-size": 1.0,
            "popup-rounding": 0.0,
            "scrollbar-rounding": 9.0,
            "scrollbar-size": 14.0,
            "selectable-text-align": [
                0.0,
                0.0
            ],
            "tab-rounding": 4.0,
            "window-border-size": 1.0,
            "window-min-size": [
                32.0,
                32.0
            ],
            "window-padding": [
                8.0,
                8.0
            ],
            "window-rounding": 0.0,
            "window-title-align": [
                0.0,
                0.5
            ],
            "window-shadow-size": 64.0,
            "window-shadow-offset": 0.0,
            "window-shadow-angle": 0.0
        },
        "imnodes": {
            "grid-spacing": 24.0,
            "link-hover-distance": 10.0,
            "link-line-segments-per-length": 0.1,
            "link-thickness": 3.0,
            "mini-map-offset": [
                4.0,
                4.0
            ],
            "mini-map-padding": [
                8.0,
                8.0
            ],
            "node-border-thickness": 1.0,
            "node-corner-rounding": 4.0,
            "node-padding": [
                8.0,
                8.0
            ],
            "pin-circle-radius": 4.0,
            "pin-hover-radius": 10.0,
            "pin-line-thickness": 1.0,
            "pin-offset": 0.0,
            "pin-quad-side-length": 7.0,
            "pin-triangle-side-length": 9.5
        },
        "implot": {
            "annotation-padding": [
                2.0,
                2.0
            ],
            "digital-bit-gap": 4.0,
            "digital-bit-height": 8.0,
            "error-bar-size": 5.0,
            "error-bar-weight": 1.5,
            "fill-alpha": 1.0,
            "fit-padding": [
                0.0,
                0.0
            ],
            "label-padding": [
                5.0,
                5.0
            ],
            "legend-inner-padding": [
                5.0,
                5.0
            ],
            "legend-padding": [
                10.0,
                10.0
            ],
            "legend-spacing": [
                5.0,
                0.0
            ],
            "line-weight": 1.0,
            "major-grid-size": [
                1.0,
                1.0
            ],
            "major-tick-len": [
                10.0,
                10.0
            ],
            "major-tick-size": [
                1.0,
                1.0
            ],
            "marker-size": 4.0,
            "marker-weight": 1.0,
            "minor-alpha": 0.25,
            "minor-grid-size": [
                1.0,
                1.0
            ],
            "minor-tick-len": [
                5.0,
                5.0
            ],
            "minor-tick-size": [
                1.0,
                1.0
            ],
            "mouse-pos-padding": [
                10.0,
                10.0
            ],
            "plot-border-size": 1.0,
            "plot-default-size": [
                400.0,
                300.0
            ],
            "plot-min-size": [
                200.0,
                150.0
            ],
            "plot-padding": [
                10.0,
                10.0
            ]
        },
        "imhex": {
            "window-blur": 0.0,
            "popup-alpha": 0.65
        }
    }
}